streamlit_dimensions/__init__.py
streamlit_dimensions/frontend/build/asset-manifest.json
streamlit_dimensions/frontend/build/bootstrap.min.css
streamlit_dimensions/frontend/build/index.html
streamlit_dimensions/frontend/build/precache-manifest.017a75c43a124fca802d1e0308c94149.js
streamlit_dimensions/frontend/build/precache-manifest.a31df42ecae412362b17080fc25dde4a.js
streamlit_dimensions/frontend/build/service-worker.js
streamlit_dimensions/frontend/build/static/js/2.2d244465.chunk.js
streamlit_dimensions/frontend/build/static/js/2.2d244465.chunk.js.LICENSE.txt
streamlit_dimensions/frontend/build/static/js/2.2d244465.chunk.js.map
streamlit_dimensions/frontend/build/static/js/main.4b7d2af8.chunk.js
streamlit_dimensions/frontend/build/static/js/main.4b7d2af8.chunk.js.map
streamlit_dimensions/frontend/build/static/js/main.b48797e6.chunk.js
streamlit_dimensions/frontend/build/static/js/main.b48797e6.chunk.js.map
streamlit_dimensions/frontend/build/static/js/runtime-main.92899dd5.js
streamlit_dimensions/frontend/build/static/js/runtime-main.92899dd5.js.map
streamlit_dimensions-0.0.1.dist-info/LICENSE
streamlit_dimensions-0.0.1.dist-info/METADATA
streamlit_dimensions-0.0.1.dist-info/WHEEL
streamlit_dimensions-0.0.1.dist-info/top_level.txt
streamlit_dimensions-0.0.1.dist-info/RECORD
