Metadata-Version: 2.1
Name: streamlit-dimensions
Version: 0.0.1
Summary: A simple component that returns the dimensions of the container where it is rendered.
Home-page: https://github.com/avsolatorio/streamlit-dimensions
Author: Aivin V. Solatorio
Author-email: avsolatorio@gmail.com
License: UNKNOWN
Platform: UNKNOWN
Requires-Python: >=3.6
License-File: LICENSE
Requires-Dist: streamlit (>=0.63)
